dataruns/__init__.py
dataruns/core/__init__.py
dataruns/core/pipeline.py
dataruns/core/transforms.py
dataruns/core/types.py
dataruns/dl/__init__.py
dataruns/dl/engine.py
dataruns/source/__init__.py
dataruns/source/datasource.py
dataruns-0.2.0.dist-info/licenses/LICENSE
dataruns-0.2.0.dist-info/METADATA
dataruns-0.2.0.dist-info/WHEEL
dataruns-0.2.0.dist-info/top_level.txt
dataruns-0.2.0.dist-info/RECORD
