Metadata-Version: 2.4
Name: dataruns
Version: 0.2.0
Summary: A small library with Pandas-Like api used for function ops execution and data transforms.
Author: Daniel
License: MIT
Project-URL: Bug Tracker, https://github.com/DanielUgoAli/dataruns/issues
Project-URL: Source Code, https://github.com/DanielUgoAli/dataruns
Requires-Python: >=3.11
License-File: LICENSE
Requires-Dist: numpy>=2.2.5
Requires-Dist: openpyxl>=3.1.5
Requires-Dist: pandas>=2.2.3
Requires-Dist: requests>=2.32.3
Requires-Dist: pytest>=7.0.0
Requires-Dist: pytest-cov>=4.0.0
Requires-Dist: ruff>=0.14.1
Dynamic: license-file
